ultimate_kinetics/__init__.py
ultimate_kinetics-0.0.4.dist-info/LICENSE
ultimate_kinetics-0.0.4.dist-info/METADATA
ultimate_kinetics-0.0.4.dist-info/WHEEL
ultimate_kinetics-0.0.4.dist-info/top_level.txt
ultimate_kinetics-0.0.4.dist-info/RECORD
