Metadata-Version: 2.1
Name: ultimate-kinetics
Version: 0.0.4
Summary: Kinetics
Maintainer-email: Vincent-Alexander Scholz <VincentAlexanderScholz@users.noreply.github.com>, Steffen Hirte <shirte@users.noreply.github.com>
License: MIT License
Requires-Python: >=3.6
License-File: LICENSE
Requires-Dist: pandas >=1.2
Provides-Extra: test
Requires-Dist: pytest ; extra == 'test'
